[
    {
        "_id": "64bea0868c6fc963b742405b",
        "name": "Daisy",
        "age": 1,
        "img": "https://img.freepik.com/premium-photo/goat-with-large-horns-sits-hill-front-sunset_865967-808.jpg",
        "price": 250,
        "location": "Ranchland",
        "breed": "Saanen",
        "weight": 40,
        "label": "for sale",
        "category": "Dairy",
        "seller": "64be9343dcbe757e1b73f95b",
        "createdAt": "2023-07-24T16:02:14.247Z",
        "updatedAt": "2023-07-24T16:02:14.247Z",
        "__v": 0
    },
    {
        "_id": "64bea2278c6fc963b7424061",
        "name": "Boss",
        "age": 4,
        "img": "https://img.freepik.com/premium-photo/toggenburg-goat-looking-away-against-white-surface_191971-22978.jpg",
        "price": 250,
        "location": "Meadow Valley",
        "breed": "Angora",
        "weight": 35,
        "label": "for sale",
        "category": "Beef",
        "seller": "64be9257dcbe757e1b73f953",
        "createdAt": "2023-07-24T16:09:11.895Z",
        "updatedAt": "2023-07-24T16:09:11.895Z",
        "__v": 0
    },
    {
        "_id": "64bea1558c6fc963b742405f",
        "name": "Rocky",
        "age": 3,
        "img": "https://img.freepik.com/premium-photo/young-goat-4-months-standing-front-white-background_191971-26074.jpg",
        "price": 220,
        "location": "Countryside",
        "breed": "Nubian",
        "weight": 50,
        "label": "for sale",
        "category": "Beef",
        "seller": "64be9257dcbe757e1b73f953",
        "createdAt": "2023-07-24T16:05:41.787Z",
        "updatedAt": "2023-07-24T16:05:41.787Z",
        "__v": 0
    },
    {
        "_id": "64bea02f8c6fc963b7424053",
        "name": "Sunny",
        "age": 2,
        "img": "https://img.freepik.com/free-vector/two-goats-meadow-near-fence-with-cheese-cottage-cheese-milk-grass-realistic_1268-15881.jpg",
        "price": 200,
        "location": "Farmville",
        "breed": "Boer",
        "weight": 45,
        "label": "for sale",
        "category": "DualPurpose",
        "seller": "64be9343dcbe757e1b73f95b",
        "createdAt": "2023-07-24T16:00:47.208Z",
        "updatedAt": "2023-07-24T16:00:47.208Z",
        "__v": 0
    },
    {
        "_id": "64bf49291946066e95c3cccd",
        "name": "Lali",
        "age": 2,
        "img": "https://img.freepik.com/free-vector/eid-al-adha-mubarak-festival-islamic-background_1055-17814.jpg",
        "price": 200,
        "location": "Barishal",
        "breed": "Pygmy",
        "weight": 25,
        "label": "for sale",
        "category": "DualPurpose",
        "seller": "64be9343dcbe757e1b73f95b",
        "createdAt": "2023-07-25T04:01:45.692Z",
        "updatedAt": "2023-07-25T04:01:45.692Z",
        "__v": 0
    },
    {
        "_id": "64bea2d88c6fc963b7424063",
        "name": "Kalu",
        "age": 2,
        "img": "https://img.freepik.com/premium-photo/young-goat-4-months-standing-front-white_191971-22276.jpg",
        "price": 190,
        "location": "Pastureland",
        "breed": "Pygmy",
        "weight": 25,
        "label": "for sale",
        "category": "Beef",
        "seller": "64be9343dcbe757e1b73f95b",
        "createdAt": "2023-07-24T16:12:08.313Z",
        "updatedAt": "2023-07-24T16:12:08.313Z",
        "__v": 0
    }
]